<?xml version="1.0" encoding="utf-8"?>
<search>
  
  
  
  <entry>
    <title>java面试</title>
    <link href="/2023/07/02/java%E9%9D%A2%E8%AF%95/"/>
    <url>/2023/07/02/java%E9%9D%A2%E8%AF%95/</url>
    
    <content type="html"><![CDATA[<h2 id="什么时jiava"><a href="#什么时jiava" class="headerlink" title="什么时jiava"></a>什么时jiava</h2>]]></content>
    
    
    <categories>
      
      <category>java</category>
      
    </categories>
    
    
    <tags>
      
      <tag>java</tag>
      
    </tags>
    
  </entry>
  
  
  
  
</search>
